synthius/__init__.py
synthius/automation/__init__.py
synthius/automation/metrics_map.py
synthius/automation/models.py
synthius/automation/pipeline.py
synthius/data/__init__.py
synthius/data/continuous_transformer.py
synthius/data/data_imputer.py
synthius/data/encoder.py
synthius/data/uniform_encoder.py
synthius/metric/__init__.py
synthius/metric/advanced_quality.py
synthius/metric/basic_quality.py
synthius/metric/distance.py
synthius/metric/likelihood.py
synthius/metric/linkability.py
synthius/metric/privacy_against_inference.py
synthius/metric/propensity.py
synthius/metric/singlingout.py
synthius/metric/utils/__init__.py
synthius/metric/utils/base_metric.py
synthius/metric/utils/utils.py
synthius/model/__init__.py
synthius/model/arf.py
synthius/model/autogloun.py
synthius/model/gaussian_multivariate.py
synthius/model/wgan.py
synthius/utilities/__init__.py
synthius/utilities/metric_evaluator.py
synthius-0.2.0.dist-info/METADATA
synthius-0.2.0.dist-info/WHEEL
synthius-0.2.0.dist-info/RECORD
