Metadata-Version: 2.3
Name: synthius
Version: 0.2.0
Summary: A toolkit for generating and evaluating synthetic data in terms of utility, privacy, and similarity
License: MIT
Keywords: synthetic data,privacy,utility,similarity,fidelity,machine learning
Author: Maryam Mohebi
Author-email: maryam@mohebi.me
Requires-Python: >=3.10,<3.12
Classifier: License :: OSI Approved :: MIT License
Classifier: Programming Language :: Python :: 3
Classifier: Programming Language :: Python :: 3.10
Classifier: Programming Language :: Python :: 3.11
Requires-Dist: anonymeter (>=1.0.0,<2.0.0)
Requires-Dist: arfpy (>=0.1.1,<0.2.0)
Requires-Dist: autogluon-tabular[all] (>=1.1.1,<2.0.0)
Requires-Dist: pandas (>=2.2.2,<3.0.0)
Requires-Dist: pomegranate (==0.15.0)
Requires-Dist: scikit-learn (>=1.4.0,<2.0.0)
Requires-Dist: sdmetrics (>=0.15.0,<0.16.0)
Requires-Dist: sdv (>=1.15.0,<2.0.0)
Requires-Dist: tensorflow (==2.16.2)
Requires-Dist: torch (==2.2.2)
Requires-Dist: tqdm (>=4.66.4,<5.0.0)
Project-URL: Homepage, https://github.com/calgo-lab/Synthius
Project-URL: Repository, https://github.com/calgo-lab/Synthius
